{
  "project_title": "Scalable E-Commerce Platform",
  "project_summary": "A comprehensive, secure e-commerce platform with robust user management, product catalog, and advanced features supporting high performance and seamless user experience.",
  "milestones": [
    {
      "name": "Foundation & User Management",
      "description": "Set up core infrastructure, user authentication, and initial system architecture",
      "estimated_duration": "2 weeks",
      "tasks": [
        {
          "name": "Project Setup",
          "description": "Configure development environment, version control, CI/CD pipeline",
          "estimated_hours": 16,
          "dependencies": []
        },
        {
          "name": "User Authentication System",
          "description": "Implement secure registration, login, password reset with two-factor authentication",
          "estimated_hours": 40,
          "dependencies": [
            "Project Setup"
          ]
        },
        {
          "name": "Database Schema Design",
          "description": "Design and implement PostgreSQL database schema for users, roles, and permissions",
          "estimated_hours": 24,
          "dependencies": [
            "Project Setup"
          ]
        }
      ]
    },
    {
      "name": "Product Catalog & Search",
      "description": "Develop product management, catalog browsing, and advanced search capabilities",
      "estimated_duration": "2 weeks",
      "tasks": [
        {
          "name": "Product Management Backend",
          "description": "Create APIs for product CRUD operations, inventory tracking",
          "estimated_hours": 40,
          "dependencies": [
            "Database Schema Design"
          ]
        },
        {
          "name": "Search & Filtering",
          "description": "Implement advanced product search, category filtering, and pagination",
          "estimated_hours": 32,
          "dependencies": [
            "Product Management Backend"
          ]
        },
        {
          "name": "Product Image Management",
          "description": "Develop image upload, optimization, and CDN integration",
          "estimated_hours": 24,
          "dependencies": [
            "Product Management Backend"
          ]
        }
      ]
    },
    {
      "name": "Shopping Experience",
      "description": "Implement shopping cart, wishlist, and interactive product features",
      "estimated_duration": "2 weeks",
      "tasks": [
        {
          "name": "Shopping Cart System",
          "description": "Develop cart management, product addition/removal, price calculations",
          "estimated_hours": 32,
          "dependencies": [
            "Product Management Backend"
          ]
        },
        {
          "name": "Product Reviews & Ratings",
          "description": "Create system for user reviews, ratings, and display mechanisms",
          "estimated_hours": 24,
          "dependencies": [
            "User Authentication System"
          ]
        },
        {
          "name": "Wishlist Functionality",
          "description": "Implement user wishlist creation, management, and interactions",
          "estimated_hours": 16,
          "dependencies": [
            "User Authentication System"
          ]
        }
      ]
    },
    {
      "name": "Checkout & Payment",
      "description": "Develop secure payment processing, order management, and confirmation workflows",
      "estimated_duration": "2 weeks",
      "tasks": [
        {
          "name": "Payment Gateway Integration",
          "description": "Implement Stripe payment processing with multiple payment method support",
          "estimated_hours": 40,
          "dependencies": [
            "Shopping Cart System"
          ]
        },
        {
          "name": "Order Processing System",
          "description": "Create order tracking, status management, and email confirmation workflows",
          "estimated_hours": 32,
          "dependencies": [
            "Payment Gateway Integration"
          ]
        },
        {
          "name": "Security Compliance",
          "description": "Implement PCI DSS and GDPR compliance measures",
          "estimated_hours": 24,
          "dependencies": [
            "Payment Gateway Integration"
          ]
        }
      ]
    },
    {
      "name": "Administration & Integrations",
      "description": "Build admin dashboard, third-party integrations, and final performance optimizations",
      "estimated_duration": "2 weeks",
      "tasks": [
        {
          "name": "Admin Dashboard",
          "description": "Develop comprehensive store management interface with role-based access",
          "estimated_hours": 40,
          "dependencies": [
            "User Authentication System"
          ]
        },
        {
          "name": "Third-Party Integrations",
          "description": "Integrate Google Analytics, Mailchimp, Zendesk, and social login",
          "estimated_hours": 32,
          "dependencies": [
            "Admin Dashboard"
          ]
        },
        {
          "name": "Performance Optimization",
          "description": "Implement caching, CDN configuration, and performance monitoring",
          "estimated_hours": 24,
          "dependencies": [
            "Third-Party Integrations"
          ]
        }
      ]
    }
  ],
  "tech_stack": [
    "React",
    "TypeScript",
    "Node.js",
    "Express",
    "PostgreSQL",
    "Redis",
    "Stripe",
    "AWS S3",
    "Google Analytics",
    "Mailchimp",
    "Zendesk",
    "GraphQL",
    "Docker"
  ],
  "open_questions": [
    "What are the specific requirements for warehouse system integration?",
    "Are there any specific payment methods required beyond Stripe?",
    "What are the exact performance benchmarks for page load times?",
    "Do we need support for international currencies and languages?"
  ],
  "estimated_total_duration": "8-10 weeks"
}